pytpixel/__init__.py
pytpixel/bans.py
pytpixel/boosters.py
pytpixel/guild.py
pytpixel/player.py
pytpixel/skyblock.py
pytpixel/translator.py
pytpixel-0.1.3.dist-info/LICENSE
pytpixel-0.1.3.dist-info/METADATA
pytpixel-0.1.3.dist-info/WHEEL
pytpixel-0.1.3.dist-info/top_level.txt
pytpixel-0.1.3.dist-info/RECORD
