Metadata-Version: 2.1
Name: pytpixel
Version: 0.1.3
Summary: A python wrapper for Hypixel's API
Home-page: https://github.com/LSOffice/Hypixel-API-Package
Author: LSOffice
Author-email: lsoffice.noreply@gmail.com
License: UNKNOWN
Platform: UNKNOWN
Classifier: Programming Language :: Python :: 3
Classifier: License :: OSI Approved :: MIT License
Classifier: Operating System :: OS Independent
Requires-Python: >=3.6
Requires-Dist: requests
